toml_init/__init__.py
toml_init/__main__.py
toml_init/encryption_manager.py
toml_init/exceptions.py
toml_init/manager.py
toml_init/utils.py
toml_init/validators.py
toml_init-0.1.5.dist-info/licenses/LICENSE.txt
toml_init-0.1.5.dist-info/METADATA
toml_init-0.1.5.dist-info/WHEEL
toml_init-0.1.5.dist-info/entry_points.txt
toml_init-0.1.5.dist-info/top_level.txt
toml_init-0.1.5.dist-info/RECORD
