Metadata-Version: 2.4
Name: toml-init
Version: 0.1.5
Summary: A library to auto-create and validate TOML configuration files from templates
Author-email: Derek Banker <dbb2002@gmail.com>
License-Expression: Apache-2.0
Project-URL: Homepage, https://github.com/Derek-Banker/TOML-Init
Project-URL: Bug Tracker, https://github.com/Derek-Banker/TOML-Init/issues
Keywords: toml,configuration,validation
Classifier: Programming Language :: Python :: 3
Classifier: Operating System :: OS Independent
Requires-Python: >=3.7
License-File: LICENSE.txt
Requires-Dist: pytomlpp>=1.0.0
Dynamic: license-file
